{
  "categories": [
    "Default"
  ],
  "lists": [
    {
      "name": "Main List",
      "items": [
        {
          "name": "Tesr",
          "quantity": 2,
          "checked": false,
          "category": "Default"
        },
        {
          "name": "Teset",
          "quantity": 1,
          "checked": false,
          "category": "Default"
        },
        {
          "name": "ASDSEA",
          "quantity": 1,
          "checked": false,
          "category": "Default"
        }
      ]
    }
  ]
}